{
    "ads": [
        {
            "title": "1 استخدام در پنج ردیف شغلی با حقوق بالا ",
            "url": "#",
            "publisher": "شرکت داروسازی رازی",
            "regions": "تهران",
            "date": "۱۳۹۹/۱۱/۲۰"
        },
        {
            "title": "2 استخدام در پنج ردیف شغلی با حقوق بالا ",
            "url": "#",
            "publisher": "شرکت داروسازی رازی",
            "regions": "تهران",
            "date": "۱۳۹۹/۱۱/۲۰"
        },
        {
            "title": "3 استخدام در پنج ردیف شغلی با حقوق بالا ",
            "url": "#",
            "publisher": "شرکت داروسازی رازی",
            "regions": "تهران",
            "date": "۱۳۹۹/۱۱/۲۰"
        },
        {
            "title": "4 استخدام در پنج ردیف شغلی با حقوق بالا ",
            "url": "#",
            "publisher": "شرکت داروسازی رازی",
            "regions": "تهران",
            "date": "۱۳۹۹/۱۱/۲۰"
        },
        {
            "title": "5 استخدام در پنج ردیف شغلی با حقوق بالا ",
            "url": "#",
            "publisher": "شرکت داروسازی رازی",
            "regions": "تهران",
            "date": "۱۳۹۹/۱۱/۲۰"
        },
        {
            "title": "6 استخدام در پنج ردیف شغلی با حقوق بالا ",
            "url": "#",
            "publisher": "شرکت داروسازی رازی",
            "regions": "تهران",
            "date": "۱۳۹۹/۱۱/۲۰"
        },
        {
            "title": "7 استخدام در پنج ردیف شغلی با حقوق بالا ",
            "url": "#",
            "publisher": "شرکت داروسازی رازی",
            "regions": "تهران",
            "date": "۱۳۹۹/۱۱/۲۰"
        },
        {
            "title": "8 استخدام در پنج ردیف شغلی با حقوق بالا ",
            "url": "#",
            "publisher": "شرکت داروسازی رازی",
            "regions": "تهران",
            "date": "۱۳۹۹/۱۱/۲۰"
        },
        {
            "title": "9 استخدام در پنج ردیف شغلی با حقوق بالا ",
            "url": "#",
            "publisher": "شرکت داروسازی رازی",
            "regions": "تهران",
            "date": "۱۳۹۹/۱۱/۲۰"
        },
        {
            "title": "10 استخدام در پنج ردیف شغلی با حقوق بالا ",
            "url": "#",
            "publisher": "شرکت داروسازی رازی",
            "regions": "تهران",
            "date": "۱۳۹۹/۱۱/۲۰"
        },
        {
            "title": "11 استخدام در پنج ردیف شغلی با حقوق بالا ",
            "url": "#",
            "publisher": "شرکت داروسازی رازی",
            "regions": "تهران",
            "date": "۱۳۹۹/۱۱/۲۰"
        },
        {
            "title": "12 استخدام در پنج ردیف شغلی با حقوق بالا ",
            "url": "#",
            "publisher": "شرکت داروسازی رازی",
            "regions": "تهران",
            "date": "۱۳۹۹/۱۱/۲۰"
        },
        {
            "title": "13 استخدام در پنج ردیف شغلی با حقوق بالا ",
            "url": "#",
            "publisher": "شرکت داروسازی رازی",
            "regions": "تهران",
            "date": "۱۳۹۹/۱۱/۲۰"
        }
    ],
    "regions":[
        "آذربایجان شرقی",
        "آذربایجان غربی",
        "اردبیل",
        "اصفهان",
        "البرز",
        "ایلام",
        "بوشهر",
        "تهران",
        "چهارمحال و بختیاری",
        "خراسان جنوبی",
        "خراسان رضوی",
        "خراسان شمالی",
        "خوزستان",
        "زنجان",
        "سمنان",
        "سیستان و بلوچستان",
        "فارس",
        "قزوین",
        "قم",
        "کردستان",
        "کرمان",
        "کرمانشاه",
        "کهگیلویه و بویراحمد",
        "گلستان",
        "گیلان",
        "لرستان",
        "مازندران",
        "مرکزی",
        "هرمزگان",
        "همدان",
        "یزد"
    ]
}